ell/__init__.py
ell/__version__.py
ell/configurator.py
ell/contrib/__init__.py
ell/evaluation/__init__.py
ell/evaluation/evaluation.py
ell/evaluation/results.py
ell/evaluation/serialization.py
ell/evaluation/util.py
ell/lmp/__init__.py
ell/lmp/_track.py
ell/lmp/complex.py
ell/lmp/function.py
ell/lmp/simple.py
ell/lmp/tool.py
ell/models/__init__.py
ell/models/anthropic.py
ell/models/bedrock.py
ell/models/google.py
ell/models/groq.py
ell/models/ollama.py
ell/models/openai.py
ell/models/xai.py
ell/provider.py
ell/providers/__init__.py
ell/providers/anthropic.py
ell/providers/bedrock.py
ell/providers/google.py
ell/providers/groq.py
ell/providers/openai.py
ell/py.typed
ell/stores/__init__.py
ell/stores/migrations/README.md
ell/stores/migrations/__init__.py
ell/stores/migrations/env.py
ell/stores/migrations/make.py
ell/stores/migrations/script.py.mako
ell/stores/migrations/versions/4524fb60d23e_initial_ell_sql_schema.py
ell/stores/migrations/versions/f6528d04bbbd_evaluations.py
ell/stores/models/__init__.py
ell/stores/models/core.py
ell/stores/models/evaluations.py
ell/stores/sql.py
ell/stores/store.py
ell/studio/__init__.py
ell/studio/__main__.py
ell/studio/config.py
ell/studio/connection_manager.py
ell/studio/datamodels.py
ell/studio/server.py
ell/studio/static/asset-manifest.json
ell/studio/static/favicon.ico
ell/studio/static/gif.gif
ell/studio/static/index.html
ell/studio/static/logo192.png
ell/studio/static/logo512.png
ell/studio/static/manifest.json
ell/studio/static/robots.txt
ell/studio/static/static/css/main.d53ca8dd.css
ell/studio/static/static/css/main.d53ca8dd.css.map
ell/studio/static/static/js/453.2fdb1dbc.chunk.js
ell/studio/static/static/js/453.2fdb1dbc.chunk.js.map
ell/studio/static/static/js/main.5c01ed9c.js
ell/studio/static/static/js/main.5c01ed9c.js.LICENSE.txt
ell/studio/static/static/js/main.5c01ed9c.js.map
ell/types/__init__.py
ell/types/_lstr.py
ell/types/lmp.py
ell/types/message.py
ell/util/WARNING
ell/util/__init__.py
ell/util/_warnings.py
ell_ai-0.0.16.dist-info/LICENSE
ell_ai-0.0.16.dist-info/METADATA
ell_ai-0.0.16.dist-info/WHEEL
ell_ai-0.0.16.dist-info/entry_points.txt
ell_ai-0.0.16.dist-info/RECORD
