Metadata-Version: 2.3
Name: ell-ai
Version: 0.0.16
Summary: ell - the language model programming library
License: MIT
Author: William Guss
Author-email: will@lrsys.xyz
Requires-Python: >=3.9
Classifier: Development Status :: 3 - Alpha
Classifier: Intended Audience :: Developers
Classifier: License :: OSI Approved :: MIT License
Classifier: Programming Language :: Python :: 3
Classifier: Programming Language :: Python :: 3.9
Classifier: Programming Language :: Python :: 3.10
Classifier: Programming Language :: Python :: 3.11
Classifier: Programming Language :: Python :: 3.12
Classifier: Programming Language :: Python :: 3.13
Classifier: Programming Language :: Python :: 3.7
Classifier: Programming Language :: Python :: 3.8
Provides-Extra: all
Provides-Extra: anthropic
Provides-Extra: google
Provides-Extra: groq
Provides-Extra: postgres
Provides-Extra: sqlite
Provides-Extra: studio
Requires-Dist: alembic (>=1.14.0,<2.0.0) ; extra == "sqlite" or extra == "postgres" or extra == "studio" or extra == "all"
Requires-Dist: anthropic (>=0.34.2,<0.35.0) ; extra == "anthropic" or extra == "all"
Requires-Dist: black (>=24.8.0,<25.0.0)
Requires-Dist: cattrs (>=23.2.3,<24.0.0)
Requires-Dist: colorama (>=0.4.6,<0.5.0)
Requires-Dist: dill (>=0.3.8,<0.4.0)
Requires-Dist: fastapi (>=0.111.1,<0.112.0) ; extra == "studio" or extra == "all"
Requires-Dist: google-genai (>=1.2.0,<2.0.0) ; extra == "google" or extra == "all"
Requires-Dist: groq (>=0.11.0,<0.12.0) ; extra == "groq" or extra == "all"
Requires-Dist: numpy (>=1.26.0)
Requires-Dist: openai (>=1.51.0,<2.0.0)
Requires-Dist: pillow (>=10.4.0,<11.0.0)
Requires-Dist: psutil (>=5.9.0,<6.0.0)
Requires-Dist: psycopg2 (>=2.7) ; extra == "postgres"
Requires-Dist: requests (>=2.32.3,<3.0.0)
Requires-Dist: sqlmodel (>=0.0.21,<0.1.0) ; extra == "sqlite" or extra == "postgres" or extra == "studio" or extra == "all"
Requires-Dist: typing-extensions (>=4.12.2,<5.0.0)
Requires-Dist: uvicorn (>=0.30.3,<0.31.0) ; extra == "studio" or extra == "all"
Project-URL: Homepage, https://docs.ell.so
Project-URL: Repository, https://github.com/MadcowD/ell
